{"cameraMode":{"drawMode":0,"name":"Shaded","section":"Shading Mode"},"sceneLighting":true,"audioPlay":false,"sceneViewState":{"showFog":true,"showMaterialUpdate":false,"showSkybox":true,"showFlares":true,"showImageEffects":true,"showParticleSystems":true},"in2DMode":false,"pivot":{"x":-4.567783355712891,"y":-4.4966864585876469,"z":-3.899421453475952},"rotation":{"x":0.32623305916786196,"y":0.6240161061286926,"z":-0.32154446840286257,"w":0.6330825686454773},"size":6.636763095855713,"orthographic":false}